coin_valid/__init__.py
coin_valid/coins.py
coin_valid/detect.py
coin_valid/exceptions/__init__.py
coin_valid/exceptions/address_exceptions.py
coin_valid/exceptions/coin_exceptions.py
coin_valid/exceptions/network_exceptions.py
coin_valid/utils.py
coin_valid/validate.py
coin_valid-0.2.0.dist-info/LICENSE
coin_valid-0.2.0.dist-info/METADATA
coin_valid-0.2.0.dist-info/WHEEL
coin_valid-0.2.0.dist-info/RECORD
