Metadata-Version: 2.1
Name: coin-valid
Version: 0.2.0
Summary: Crypto Currency address validation library
Home-page: https://notmtth.codeberg.page/coin-valid
License: GPL-3
Keywords: cryptocurrency,validation,bitcoin,etherum,monero
Author: NotMtth
Author-email: notmtth@xmpp.is
Requires-Python: >=3.10,<4.0
Classifier: License :: Other/Proprietary License
Classifier: Programming Language :: Python :: 3
Classifier: Programming Language :: Python :: 3.10
Classifier: Programming Language :: Python :: 3.11
Requires-Dist: mkdocs (>=1.4.3,<2.0.0)
Requires-Dist: mkdocs-material (>=9.1.15,<10.0.0)
Project-URL: Repository, https://codeberg.org/NotMtth/coin-valid
